easy_enum.py
easy_enum-0.3.0.dist-info/LICENSE
easy_enum-0.3.0.dist-info/METADATA
easy_enum-0.3.0.dist-info/WHEEL
easy_enum-0.3.0.dist-info/top_level.txt
easy_enum-0.3.0.dist-info/RECORD
