Metadata-Version: 2.1
Name: easy-enum
Version: 0.3.0
Summary: User friendly implementation of Enum in Python
Home-page: https://github.com/molejar/pyEnum
Author: Martin Olejar
Author-email: martin.olejar@gmail.com
License: Apache 2.0
Platform: UNKNOWN
Classifier: Operating System :: OS Independent
Classifier: Programming Language :: Python :: 3
Classifier: License :: OSI Approved :: Apache Software License
Classifier: Topic :: Scientific/Engineering
Classifier: Topic :: Software Development
Classifier: Topic :: Utilities
